chaos_forge/__init__.py
chaos_forge/simulator.py
core/__init__.py
core/decorators.py
core/error_handling.py
core/persistence.py
core/rafael_engine.py
devkit/__init__.py
devkit/cli.py
guardian/__init__.py
guardian/guardian_layer.py
rafael_framework-1.2.0.dist-info/licenses/LICENSE
vault/__init__.py
vault/resilience_vault.py
rafael_framework-1.2.0.dist-info/METADATA
rafael_framework-1.2.0.dist-info/WHEEL
rafael_framework-1.2.0.dist-info/entry_points.txt
rafael_framework-1.2.0.dist-info/top_level.txt
rafael_framework-1.2.0.dist-info/RECORD
