Metadata-Version: 2.4
Name: rafael-framework
Version: 1.2.0
Summary: Resilience-Adaptive Framework for Autonomous Evolution & Learning
Home-page: https://github.com/Rafael2022-prog/rafael
Author: RAFAEL Team
Author-email: RAFAEL Team <info@rafaelabs.xyz>
Maintainer: RAFAEL Framework
Maintainer-email: RAFAEL Framework <info@rafaelabs.xyz>
License: Proprietary
Project-URL: Homepage, https://github.com/Rafael2022-prog/rafael
Project-URL: Documentation, https://github.com/Rafael2022-prog/rafael/tree/main/docs
Project-URL: Repository, https://github.com/Rafael2022-prog/rafael
Project-URL: Bug Tracker, https://github.com/Rafael2022-prog/rafael/issues
Keywords: resilience,chaos-engineering,antifragile,adaptive-systems,evolution,machine-learning,devops,reliability
Classifier: Development Status :: 4 - Beta
Classifier: Intended Audience :: Developers
Classifier: Topic :: Software Development :: Libraries :: Application Frameworks
Classifier: Topic :: System :: Monitoring
Classifier: Topic :: System :: Distributed Computing
Classifier: License :: Other/Proprietary License
Classifier: Programming Language :: Python :: 3
Classifier: Programming Language :: Python :: 3.8
Classifier: Programming Language :: Python :: 3.9
Classifier: Programming Language :: Python :: 3.10
Classifier: Programming Language :: Python :: 3.11
Classifier: Programming Language :: Python :: 3.12
Requires-Python: >=3.8
License-File: LICENSE
Requires-Dist: click>=8.0.0
Provides-Extra: dev
Requires-Dist: pytest>=7.0.0; extra == "dev"
Requires-Dist: pytest-asyncio>=0.20.0; extra == "dev"
Requires-Dist: black>=22.0.0; extra == "dev"
Requires-Dist: flake8>=4.0.0; extra == "dev"
Requires-Dist: mypy>=0.950; extra == "dev"
Provides-Extra: web
Requires-Dist: fastapi>=0.95.0; extra == "web"
Requires-Dist: uvicorn>=0.20.0; extra == "web"
Provides-Extra: all
Requires-Dist: rafael-framework[dev,web]; extra == "all"
Dynamic: author
Dynamic: home-page
Dynamic: license-file
Dynamic: maintainer
Dynamic: requires-python
